opensquat/__init__.py
opensquat/app.py
opensquat/arg_parser.py
opensquat/check_update.py
opensquat/ct.py
opensquat/dns_resolvers.py
opensquat/file_input.py
opensquat/homograph.py
opensquat/output.py
opensquat/phishing.py
opensquat/port_check.py
opensquat/validations.py
opensquat/vt.py
tests/__init__.py
tests/test_ct.py
tests/test_validations.py
opensquat-2.2.dist-info/LICENSE
opensquat-2.2.dist-info/METADATA
opensquat-2.2.dist-info/WHEEL
opensquat-2.2.dist-info/top_level.txt
opensquat-2.2.dist-info/RECORD
