Metadata-Version: 2.1
Name: opensquat
Version: 2.2
Summary: The openSquat is a tool for detecting phishing domains and domain squatting.
Home-page: http://github.com/atenreiro/opensquat
Author: Andre Tenreiro
Author-email: andre@opensquat.com
License: GPLv3
License-File: LICENSE
Requires-Dist: strsimpy
Requires-Dist: confusable-homoglyphs
Requires-Dist: homoglyphs
Requires-Dist: colorama
Requires-Dist: requests
Requires-Dist: numpy
Requires-Dist: pytest
Requires-Dist: pytest-cov
Requires-Dist: codecov
Requires-Dist: coverage
Requires-Dist: black
Requires-Dist: flake8
Requires-Dist: beautifulsoup4
Requires-Dist: dnspython
Requires-Dist: packaging
